workbench/__init__.py
workbench/algorithms/__init__.py
workbench/algorithms/dataframe/Readme.md
workbench/algorithms/dataframe/__init__.py
workbench/algorithms/dataframe/compound_dataset_overlap.py
workbench/algorithms/dataframe/data_source_eda.py
workbench/algorithms/dataframe/feature_space_proximity.py
workbench/algorithms/dataframe/fingerprint_proximity.py
workbench/algorithms/dataframe/projection_2d.py
workbench/algorithms/dataframe/proximity.py
workbench/algorithms/dataframe/smart_aggregator.py
workbench/algorithms/dataframe/storage/aggregation.py
workbench/algorithms/dataframe/storage/feature_resolution.py
workbench/algorithms/dataframe/storage/feature_spider.py
workbench/algorithms/dataframe/storage/residuals_calculator.py
workbench/algorithms/dataframe/storage/row_tagger.py
workbench/algorithms/dataframe/storage/target_gradients.py
workbench/algorithms/graph/__init__.py
workbench/algorithms/graph/heavy/Readme.md
workbench/algorithms/graph/light/Readme.md
workbench/algorithms/graph/light/__init__.py
workbench/algorithms/graph/light/proximity_graph.py
workbench/algorithms/models/cleanlab_model.py
workbench/algorithms/models/noise_model.py
workbench/algorithms/spark/Readme.md
workbench/algorithms/sql/Readme.md
workbench/algorithms/sql/__init__.py
workbench/algorithms/sql/column_stats.py
workbench/algorithms/sql/correlations.py
workbench/algorithms/sql/descriptive_stats.py
workbench/algorithms/sql/outliers.py
workbench/algorithms/sql/sample_rows.py
workbench/algorithms/sql/value_counts.py
workbench/api/__init__.py
workbench/api/compound.py
workbench/api/data_source.py
workbench/api/df_store.py
workbench/api/endpoint.py
workbench/api/feature_set.py
workbench/api/graph_store.py
workbench/api/meta.py
workbench/api/meta_model.py
workbench/api/model.py
workbench/api/monitor.py
workbench/api/parameter_store.py
workbench/api/pipeline.py
workbench/cached/__init__.py
workbench/cached/cached_data_source.py
workbench/cached/cached_endpoint.py
workbench-0.8.245.dist-info/licenses/LICENSE
workbench-0.8.245.dist-info/METADATA
workbench-0.8.245.dist-info/WHEEL
workbench-0.8.245.dist-info/entry_points.txt
workbench-0.8.245.dist-info/top_level.txt
workbench-0.8.245.dist-info/RECORD
