Metadata-Version: 2.4
Name: workbench
Version: 0.8.245
Summary: Workbench: A Dashboard and Python API for creating and deploying AWS SageMaker Model Pipelines
Author-email: SuperCowPowers LLC <support@supercowpowers.com>
License: MIT License
Project-URL: Homepage, https://github.com/SuperCowPowers/workbench
Keywords: SageMaker,Machine Learning,AWS,Python,Utilities
Classifier: Development Status :: 4 - Beta
Classifier: Programming Language :: Python :: 3.10
Classifier: Programming Language :: Python :: 3.11
Classifier: Programming Language :: Python :: 3.12
Classifier: Programming Language :: Python :: 3.13
Classifier: Topic :: Scientific/Engineering
Requires-Python: >=3.10
License-File: LICENSE
Requires-Dist: boto3>=1.31.76
Requires-Dist: botocore>=1.31.76
Requires-Dist: redis>=5.0.1
Requires-Dist: numpy>=1.26.4
Requires-Dist: pandas<3.0,>=2.2.1
Requires-Dist: awswrangler>=3.4.0
Requires-Dist: sagemaker<3.0,>=2.143
Requires-Dist: cryptography>=44.0.2
Requires-Dist: ipython>=8.37.0
Requires-Dist: pyreadline3; sys_platform == "win32"
Requires-Dist: scikit-learn>=1.5.2
Requires-Dist: umap-learn>=0.5.8
Requires-Dist: xgboost>=3.0.3
Requires-Dist: joblib>=1.3.2
Requires-Dist: requests>=2.26.0
Requires-Dist: rdkit>=2024.9.5
Requires-Dist: mordredcommunity>=2.0.6
Requires-Dist: workbench-bridges>=0.1.16
Requires-Dist: cleanlab>=2.9.0
Provides-Extra: ui
Requires-Dist: plotly>=6.0.0; extra == "ui"
Requires-Dist: dash>=3.0.0; extra == "ui"
Requires-Dist: dash-bootstrap-components>=1.6.0; extra == "ui"
Requires-Dist: dash-bootstrap-templates>=1.3.0; extra == "ui"
Requires-Dist: dash_ag_grid>=33.3.3; extra == "ui"
Requires-Dist: tabulate>=0.9.0; extra == "ui"
Requires-Dist: matplotlib>=3.9.2; extra == "ui"
Provides-Extra: dev
Requires-Dist: pytest; extra == "dev"
Requires-Dist: pytest-sugar; extra == "dev"
Requires-Dist: coverage; extra == "dev"
Requires-Dist: pytest-cov; extra == "dev"
Requires-Dist: flake8; extra == "dev"
Requires-Dist: black; extra == "dev"
Provides-Extra: all
Requires-Dist: networkx>=3.2; extra == "all"
Requires-Dist: workbench[ui]; extra == "all"
Requires-Dist: workbench[dev]; extra == "all"
Dynamic: license-file
